[
    {
        "title": "JPMorgan Says Ethereum Will Outperform Bitcoin In 2024",
        "snippet": "The analysts reason that the Ethereum EIP-4844 upgrade, also known as the Proto-Danksharding upgrade, is expected to take place during the first half of 2024 ...",
        "highlighted_words": [
            "Ethereum EIP-4844 upgrade"
        ],
        "position": 1,
        "date": "Dec 20, 2023",
        "sentiment": "negative",
        "probs": {
            "neg": 0.5968069732189178,
            "neu": 0.020280951634049416,
            "pos": 0.3829120798036456
        }
    },
    {
        "title": "Ethereum to \u201cEasily\u201d Rally 350% and Hit $10000",
        "snippet": "According to cryptocurrency analyst Altcoin Daily, Ethereum (ETH) can \u201ceasily\u201d hit $10,000, a rise of about 354% from current levels. The analyst took to X and ...",
        "highlighted_words": [
            "Ethereum (ETH) can \u201ceasily\u201d hit $10,000"
        ],
        "position": 2,
        "date": "Dec 20, 2023",
        "sentiment": "negative",
        "probs": {
            "neg": 0.8661267459392548,
            "neu": 0.012481987476348877,
            "pos": 0.12139124795794487
        }
    },
    {
        "title": "Should I buy Ethereum in 2025? An In-Depth Analysis",
        "snippet": "Ethereum as a coin performed incredibly well, withstanding extreme market conditions, fluctuations, and volatility over the years.",
        "highlighted_words": [
            "Ethereum as a coin performed incredibly well"
        ],
        "position": 3,
        "date": "Dec 25, 2023",
        "sentiment": "neutral",
        "probs": {
            "neg": 0.49260545894503593,
            "neu": 0.012680892832577229,
            "pos": 0.4947136268019676
        }
    },
    {
        "title": "Buterin, Coinbase and more to fund Ethereum ...",
        "snippet": "The PBS Foundation is opening applications for an initial $1 million in grants for research and development on Ethereum proposer-builder separation.",
        "highlighted_words": [
            "Ethereum"
        ],
        "position": 4,
        "date": "Dec 21, 2023",
        "sentiment": "neutral",
        "probs": {
            "neg": 0.42632773146033287,
            "neu": 0.008015268482267857,
            "pos": 0.5656569600105286
        }
    },
    {
        "title": "Grayscale Ethereum Trust (ETH) ETF News",
        "snippet": "ETHE News \u00b7 Ethereum (ETH) Tests Major Breakout Zone, Analyst Anticipates $3,500 Target \u00b7 Glassnode Cofounders Set $2.5K Target for Ethereum's Ambitious Push.",
        "highlighted_words": [
            "Ethereum (ETH) Tests Major Breakout Zone, Analyst Anticipates $3,500 Target"
        ],
        "position": 5,
        "date": "Dec 25, 2023",
        "sentiment": "neutral",
        "probs": {
            "neg": 0.4937608763575554,
            "neu": 0.013250494841486216,
            "pos": 0.4929886721074581
        }
    },
    {
        "title": "Ethereum Will Make Millionaires In 2024, BUT Not How You ...",
        "snippet": "Ethereum is going to make a lot of new millionaires in 2024 but not how you think.",
        "highlighted_words": [],
        "position": 6,
        "date": "",
        "sentiment": "positive",
        "probs": {
            "neg": 0.07847101241350174,
            "neu": 0.0123835364356637,
            "pos": 0.9091454744338989
        }
    },
    {
        "title": "Ethereum ETH Staking: Earn Rewards with Coinbase",
        "snippet": "The current reward for Ethereum staking is 2.07%. Discover new staking assets to add to your portfolio and start earning rewards today.",
        "highlighted_words": [
            "The current reward for Ethereum staking is 2.07"
        ],
        "position": 7,
        "date": "Dec 21, 2023",
        "sentiment": "positive",
        "probs": {
            "neg": 0.25531189143657684,
            "neu": 0.00923696719110012,
            "pos": 0.7354511022567749
        }
    },
    {
        "title": "SOL Founder Says 'Solana Is Ethereum,' What Does He ...",
        "snippet": "SOL co-founder Anatoly Yakovenko recently highlighted the relationship between Solana and Ethereum as he said \u201cSolana is Ethereum.\u201d",
        "highlighted_words": [
            "SOL co-founder Anatoly Yakovenko"
        ],
        "position": 8,
        "date": "Dec 26, 2023",
        "sentiment": "positive",
        "probs": {
            "neg": 0.0384404556825757,
            "neu": 0.044754261150956154,
            "pos": 0.9168052673339844
        }
    },
    {
        "title": "Ethereum Issuance Expected to Decline by '90%' Post-Merge",
        "snippet": "With the Merge taking place later in 2022, Ethereum issuance is set to decline. Click here to find out why this will benefit the coin.",
        "highlighted_words": [
            "Ethereum issuance is set to decline"
        ],
        "position": 9,
        "date": "Dec 20, 2023",
        "sentiment": "neutral",
        "probs": {
            "neg": 0.008780707139521837,
            "neu": 0.9641676247119904,
            "pos": 0.027051676996052265
        }
    },
    {
        "title": "Ethereum Founder Vitalik Buterin Sells Trillions Of Tokens",
        "snippet": "Ethereum founder, Vitalik Buterin has undertaken a large-scale transaction involving trillions of meme tokens, leaving the broader cryptocurrency space ...",
        "highlighted_words": [
            "Ethereum founder, Vitalik Buterin"
        ],
        "position": 10,
        "date": "Dec 22, 2023",
        "sentiment": "positive",
        "probs": {
            "neg": 0.10774180479347706,
            "neu": 0.014312071492895484,
            "pos": 0.8779460787773132
        }
    },
    {
        "title": "Six most important crypto events to look forward to in 2024",
        "snippet": "Spot Bitcoin ETF approval in the US \u00b7 Ethereum Dencun \u00b7 The end of the US interest rate hike \u00b7 Circle IPO \u00b7 Bitcoin halving \u00b7 FTX case nearing resolution \u00b7 The road ...",
        "highlighted_words": [
            "Ethereum Dencun"
        ],
        "position": 11,
        "date": "Dec 23, 2023",
        "sentiment": "neutral",
        "probs": {
            "neg": 0.45346711575984955,
            "neu": 0.01683317543938756,
            "pos": 0.5296997204422951
        }
    },
    {
        "title": "'Narrative Shift Away From ETH': Investor Justin Bons on ...",
        "snippet": "Instead of Ethereum (ETH), all eyes are on its L1 competitors, Cyber Capital CIO Justin Bons says in a recent X post. What is happening in cryptocurrency now is ...",
        "highlighted_words": [
            "all eyes are on its L1 competitors"
        ],
        "position": 12,
        "date": "Dec 23, 2023",
        "sentiment": "positive",
        "probs": {
            "neg": 0.17940698843449354,
            "neu": 0.11522969603538513,
            "pos": 0.7053633332252502
        }
    },
    {
        "title": "Solana vs Ethereum: Key Metrics and Costs to Consider",
        "snippet": "Solana has overtaken Ethereum in key metrics like DEX volumes, NFTs, address activity, and stablecoin transfers. Running Solana nodes is 5x more expensive ...",
        "highlighted_words": [
            "Solana has overtaken Ethereum in key metrics"
        ],
        "position": 13,
        "date": "Dec 20, 2023",
        "sentiment": "positive",
        "probs": {
            "neg": 0.14016325026750565,
            "neu": 0.014034442603588104,
            "pos": 0.8458022475242615
        }
    },
    {
        "title": "Bitcoin, Ethereum, and EigenLayer - A Play in Three Acts",
        "snippet": "From Bitcoin's birth to Ethereum's expansion, the blockchain narrative unfolds through transformative platforms. John deVadoss. Dec. 23, 2023 at 8:00 pm UTC.",
        "highlighted_words": [
            "Ethereum's expansion"
        ],
        "position": 14,
        "date": "Dec 23, 2023",
        "sentiment": "positive",
        "probs": {
            "neg": 0.034788042306900024,
            "neu": 0.02663642168045044,
            "pos": 0.9385755062103271
        }
    },
    {
        "title": "7 Potential Risks and Challenges When Investing in ...",
        "snippet": "If the market buzz is positive, many investors hop on the train and buy ETH, which pushes its price up. However, bad news like a breach in security can lead ...",
        "highlighted_words": [
            "ETH",
            "news"
        ],
        "position": 15,
        "date": "Dec 21, 2023",
        "sentiment": "positive",
        "probs": {
            "neg": 0.16708340495824814,
            "neu": 0.3096086271107197,
            "pos": 0.5233079865574837
        }
    },
    {
        "title": "Bitcoin's Rally Outshines Ethereum and Other Cryptos \u2022",
        "snippet": "Bitcoin's surge, marked by a 162% increase this year, contrasts sharply with Ethereum's 93% rise and the broader crypto market's mixed results.",
        "highlighted_words": [
            "Ethereum's 93% rise"
        ],
        "position": 16,
        "date": "Dec 22, 2023",
        "sentiment": "neutral",
        "probs": {
            "neg": 0.4279608204960823,
            "neu": 0.47580029256641865,
            "pos": 0.0962388776242733
        }
    },
    {
        "title": "Testnet",
        "snippet": "Ethereum to Sunset 'Holesky' Testnet in September. The deprecation plan comes after Holesky fell offline due to a faulty test of Ethereum's upcoming Pectra ...",
        "highlighted_words": [
            "Ethereum to Sunset 'Holesky' Testnet in September"
        ],
        "position": 17,
        "date": "Dec 22, 2023",
        "sentiment": "positive",
        "probs": {
            "neg": 0.025686462875455618,
            "neu": 0.45251741353422403,
            "pos": 0.5217961370944977
        }
    },
    {
        "title": "Smart Contract Tokens Solana and Avalanche Surge ...",
        "snippet": "Over the past month, solana (SOL)has experienced a 42% surge, while avalanche (AVAX) has soared by 104% against the U.S. dollar.",
        "highlighted_words": [
            "solana (SOL)has experienced a 42% surge"
        ],
        "position": 18,
        "date": "Dec 20, 2023",
        "sentiment": "negative",
        "probs": {
            "neg": 0.6622198522090912,
            "neu": 0.014453535433858633,
            "pos": 0.32332658115774393
        }
    },
    {
        "title": "'Ethereum Killer' Solana (SOL) Records Whopping 300% ...",
        "snippet": "Solana (SOL) reshaping crypto narrative, outpacing Ethereum (ETH) with impressive 300% growth, prompting discussions on potential flippening.",
        "highlighted_words": [
            "outpacing Ethereum (ETH"
        ],
        "position": 19,
        "date": "Dec 24, 2023",
        "sentiment": "negative",
        "probs": {
            "neg": 0.8697772920131683,
            "neu": 0.013416888657957315,
            "pos": 0.11680582351982594
        }
    },
    {
        "title": "When Can I Unstake Ethereum?",
        "snippet": "Explore when and how to unstake Ethereum in our comprehensive guide and dive into the intricacies of staking and unstaking Ethereum with detailed insights.",
        "highlighted_words": [
            "Explore when and how to unstake Ethereum"
        ],
        "position": 20,
        "date": "Dec 24, 2023",
        "sentiment": "positive",
        "probs": {
            "neg": 0.06614894885569811,
            "neu": 0.022609509993344545,
            "pos": 0.9112415611743927
        }
    },
    {
        "title": "Ethereum ETH Price News Today - Technical Analysis Update ...",
        "snippet": "Ethereum ETH Price News Today - Technical Analysis Update, Price Now! Elliott Wave Price Prediction! \u00b7 Comments9. thumbnail-image. Add a comment... 9 ...",
        "highlighted_words": [],
        "position": 21,
        "date": "",
        "sentiment": "positive",
        "probs": {
            "neg": 0.04282231070101261,
            "neu": 0.02193047571927309,
            "pos": 0.9352472126483917
        }
    },
    {
        "title": "Crypto Rover: Ethereum deemed oversold sparking market ...",
        "snippet": "Crypto Rover identifies Ethereum as oversold, drawing comparisons to 2020 market conditions that saw a bullish run.",
        "highlighted_words": [
            "Ethereum as oversold"
        ],
        "position": 22,
        "date": "Dec 21, 2023",
        "sentiment": "neutral",
        "probs": {
            "neg": 0.028579494450241327,
            "neu": 0.9499739408493042,
            "pos": 0.021446523256599903
        }
    },
    {
        "title": "Ethereum Eyes $3500 as Breakout Zone Beckons Retesting",
        "snippet": "Ethereum is currently on an upward trajectory, undergoing a retest of its breakout zone within an ascending triangle. Ali identifies a crucial price range ...",
        "highlighted_words": [
            "Ethereum is currently on an upward trajectory"
        ],
        "position": 23,
        "date": "Dec 20, 2023",
        "sentiment": "negative",
        "probs": {
            "neg": 0.6162669062614441,
            "neu": 0.05777447111904621,
            "pos": 0.32595865428447723
        }
    },
    {
        "title": "Anatoly Yakovenko jokes 'Solana is Ethereum' in ironic ...",
        "snippet": "In a Dec. 25 tweet, Yakovenko playfully suggested that Solana could be considered an Ethereum layer-2 (L2) solution through its Wormhole eigenlayer.",
        "highlighted_words": [
            "Ethereum"
        ],
        "position": 24,
        "date": "Dec 26, 2023",
        "sentiment": "positive",
        "probs": {
            "neg": 0.051910048350691795,
            "neu": 0.12748249806463718,
            "pos": 0.820607453584671
        }
    },
    {
        "title": "ETHEREUM WILL GO TO ZERO, AND HERE IS WHY",
        "snippet": "In \"Ethereum Will Go to Zero, and Here's Why,\" author Richard A. Mann takes readers on a compelling journey through the highs and lows of the cryptocurrency ...",
        "highlighted_words": [
            "Ethereum"
        ],
        "position": 25,
        "date": "Dec 20, 2023",
        "sentiment": "positive",
        "probs": {
            "neg": 0.05904222372919321,
            "neu": 0.04970178380608559,
            "pos": 0.8912559747695923
        }
    },
    {
        "title": "What Crypto Users Need to Know: The ERC20 Standard",
        "snippet": "ERC20 is a standard for the Ethereum blockchain that requires certain scripting functions and two events that must be used when creating a fungible token ...",
        "highlighted_words": [
            "ERC20 is a standard for the Ethereum blockchain"
        ],
        "position": 26,
        "date": "Dec 26, 2023",
        "sentiment": "positive",
        "probs": {
            "neg": 0.02813875302672386,
            "neu": 0.023356983438134193,
            "pos": 0.9485042691230774
        }
    },
    {
        "title": "The 6 Chains Hunting Ethereum",
        "snippet": "The key Etherrum contenders are Polygon, Solana, Optimism, Avalanche, Arbitrum and Binance smart chain.",
        "highlighted_words": [],
        "position": 27,
        "date": "Dec 20, 2023",
        "sentiment": "positive",
        "probs": {
            "neg": 0.0776661615818739,
            "neu": 0.013167497236281633,
            "pos": 0.9091663062572479
        }
    },
    {
        "title": "Top Altcoins To Buy On December 20: Ethereum Express ...",
        "snippet": "Ethereum Express (ETE), Stacks (STX), and BONK emerge as top altcoins to buy in December for speculation in early 2024.",
        "highlighted_words": [
            "Ethereum"
        ],
        "position": 28,
        "date": "Dec 20, 2023",
        "sentiment": "positive",
        "probs": {
            "neg": 0.24650248140096664,
            "neu": 0.015269208699464798,
            "pos": 0.7382283210754395
        }
    },
    {
        "title": "MOLLARS presale ongoing, project building a ...",
        "snippet": "The initial coin offering for MOLLARS, a store of value token on Ethereum (ETH), is now live. Designed to serve as the new \u201cBitcoin (BTC)\u201d of the ERC-20 and ...",
        "highlighted_words": [
            "Ethereum",
            "ETH"
        ],
        "position": 29,
        "date": "Dec 22, 2023",
        "sentiment": "positive",
        "probs": {
            "neg": 0.15708698704838753,
            "neu": 0.011092011351138353,
            "pos": 0.8318209946155548
        }
    },
    {
        "title": "NFT Sales Dip \u2014 Bitcoin Dominance and Solana's Rise ...",
        "snippet": "In the last week, sales of non-fungible tokens (NFTs) have fallen by 12.26%, totaling $463.87 million, marking a decrease from the previous week.",
        "highlighted_words": [
            "sales of non-fungible tokens (NFTs) have fallen by 12.26"
        ],
        "position": 30,
        "date": "Dec 24, 2023",
        "sentiment": "neutral",
        "probs": {
            "neg": 0.07884784508496523,
            "neu": 0.5084696020931005,
            "pos": 0.4126825863495469
        }
    },
    {
        "title": "Justin Sun Withdraws $14 Million In Ethereum",
        "snippet": "Justin Sun, the person who started Tron, took out a huge amount of Ethereum (ETH), about $13.8 million, from Binance, a major crypto exchange.",
        "highlighted_words": [
            "Justin Sun, the person who started Tron"
        ],
        "position": 31,
        "date": "Dec 26, 2023",
        "sentiment": "positive",
        "probs": {
            "neg": 0.0306000760756433,
            "neu": 0.36701926961541176,
            "pos": 0.6023806929588318
        }
    },
    {
        "title": "Solana Surges to $84, Flips Ethereum in Weekly DEX Volume",
        "snippet": "Solana's native token SOL is up 580% over a one-year period, gaining 13% in the last 24 hours to trade at $84 at the time of writing.",
        "highlighted_words": [
            "Solana's native token SOL is up 580% over a one-year period"
        ],
        "position": 32,
        "date": "Dec 21, 2023",
        "sentiment": "negative",
        "probs": {
            "neg": 0.9170344173908234,
            "neu": 0.022167074494063854,
            "pos": 0.060798514634370804
        }
    },
    {
        "title": "Scott Melker evaluates Ethereum risk reward potential",
        "snippet": "Scott Melker provides analysis suggesting favorable Ethereum risk/reward ratio amidst current market volatility.",
        "highlighted_words": [
            "favorable Ethereum risk/reward ratio"
        ],
        "position": 33,
        "date": "Dec 22, 2023",
        "sentiment": "neutral",
        "probs": {
            "neg": 0.5297798104584217,
            "neu": 0.01705317758023739,
            "pos": 0.4531670017167926
        }
    },
    {
        "title": "Ethereum $2500 Price Prediction. Cardano and Borroe ...",
        "snippet": "Ethereum's pursuit of $2,500, Cardano's impressive growth, and Borroe Finance's promising presale are more than just news\u2014they're opportunities. Opportunities ...",
        "highlighted_words": [
            "Ethereum's pursuit of $2,500"
        ],
        "position": 34,
        "date": "Dec 22, 2023",
        "sentiment": "positive",
        "probs": {
            "neg": 0.18643923103809357,
            "neu": 0.012918327003717422,
            "pos": 0.8006424903869629
        }
    },
    {
        "title": "Getting Your .ETH Domain: Complete Guide to the ENS",
        "snippet": "I'm going to let you know the steps you can take to secure your own .eth domain, which will allow you to receive ETH to the Ethereum wallet of your choice.",
        "highlighted_words": [
            "domain"
        ],
        "position": 35,
        "date": "Dec 21, 2023",
        "sentiment": "positive",
        "probs": {
            "neg": 0.08950627781450748,
            "neu": 0.01679346151649952,
            "pos": 0.8937002420425415
        }
    },
    {
        "title": "Bitcoin News - X",
        "snippet": "JUST IN: Attorney and former Ethereum advisor, Steven Nerayoff, claims the infamous 2016 DAO hack was an inside job. Embedded video.",
        "highlighted_words": [
            "Ethereum"
        ],
        "position": 36,
        "date": "",
        "sentiment": "positive",
        "probs": {
            "neg": 0.02648330945521593,
            "neu": 0.1532555539160967,
            "pos": 0.820261150598526
        }
    },
    {
        "title": "SIZE (SIZE) Price Today, News & Live Chart",
        "snippet": "SIZE & Other Cryptocurrencies ; Bitcoinbtc. $93,248.00. (-0.66%) ; Ethereumeth. $1,759.95. (-1.88%) ; Tetherusdt. $1.00. (0.00%).",
        "highlighted_words": [
            "Ethereumeth. $1,759.95"
        ],
        "position": 37,
        "date": "Dec 26, 2023",
        "sentiment": "positive",
        "probs": {
            "neg": 0.03371752146631479,
            "neu": 0.02511448599398136,
            "pos": 0.9411680102348328
        }
    },
    {
        "title": "Bitcoin Trades Above $43.5K, Ether Stays Below $2300 ...",
        "snippet": "3.0 TV is a news channel which gives you the latest news on blockchain and cryptocurrency on a daily basis which include Bitcoin (BTC), Ethereum, LUNA, UST, ...",
        "highlighted_words": [],
        "position": 38,
        "date": "",
        "sentiment": "neutral",
        "probs": {
            "neg": 0.38663930632174015,
            "neu": 0.056563105434179306,
            "pos": 0.556797593832016
        }
    },
    {
        "title": "Sui | Deliver the Benefits of Web3 with the Ease of Web2",
        "snippet": "Sui is a first-of-its-kind Layer 1 blockchain and smart contract platform designed to make digital asset ownership fast, private, secure, and accessible.",
        "highlighted_words": [
            "Sui"
        ],
        "position": 39,
        "date": "Dec 21, 2023",
        "sentiment": "positive",
        "probs": {
            "neg": 0.333380613476038,
            "neu": 0.009550291579216719,
            "pos": 0.6570691168308258
        }
    },
    {
        "title": "MiCA: EU's Comprehensive Crypto Regulation Explained",
        "snippet": "MiCA (Markets in Crypto-Assets) is a EU legislation that stablishes the first comprehensive global regulatory framework for crypto assets.",
        "highlighted_words": [
            "MiCA (Markets in Crypto-Assets"
        ],
        "position": 40,
        "date": "Dec 20, 2023",
        "sentiment": "positive",
        "probs": {
            "neg": 0.07447720691561699,
            "neu": 0.01528287073597312,
            "pos": 0.9102399051189423
        }
    },
    {
        "title": "Altcoins News - Latest news | The ...",
        "snippet": "In an unexpected turn of events within the blockchain community, BloXroute Labs, a major player in Ethereum... Steven Anderson December 20, 2023.",
        "highlighted_words": [
            "Ethereum"
        ],
        "position": 41,
        "date": "Dec 20, 2023",
        "sentiment": "positive",
        "probs": {
            "neg": 0.06861602887511253,
            "neu": 0.032853164710104465,
            "pos": 0.8985307812690735
        }
    },
    {
        "title": "Shibtoken",
        "snippet": "Shiba Inu (SHIB) is our key token, embodying a global, decentralized, community-driven currency. Launched in 2020, this Ethereum-based token is a global ...",
        "highlighted_words": [
            "Ethereum"
        ],
        "position": 42,
        "date": "Dec 26, 2023",
        "sentiment": "positive",
        "probs": {
            "neg": 0.12908030301332474,
            "neu": 0.02095321100205183,
            "pos": 0.8499664962291718
        }
    },
    {
        "title": "AltLayer Introduces Restaked Rollups | Ethereum News",
        "snippet": "Ethereum News Roundup for Wednesday, December 20, 2023: AltLayer introduces restaked rollups. EspressoSys releases a roadmap for Timeboost.",
        "highlighted_words": [],
        "position": 43,
        "date": "",
        "sentiment": "positive",
        "probs": {
            "neg": 0.04032664932310581,
            "neu": 0.022377180866897106,
            "pos": 0.9372962117195129
        }
    },
    {
        "title": "Homepage - Institute of Geodesy and Photogrammetry ...",
        "snippet": "News. Sentinel satellites. Our earth observation projects with satellites are featured in the ETH news and ETH Globe. external page More. Space eXchange ...",
        "highlighted_words": [
            "ETH news"
        ],
        "position": 44,
        "date": "Dec 23, 2023",
        "sentiment": "positive",
        "probs": {
            "neg": 0.03163719456642866,
            "neu": 0.017667533364146948,
            "pos": 0.9506953060626984
        }
    },
    {
        "title": "Bellscoin Price: BELLS Live Price Chart, Market Cap & ...",
        "snippet": "Track the latest Bellscoin price, market cap, trading volume, news and more with CoinGecko's live BELLS price chart and popular ...",
        "highlighted_words": [
            "news"
        ],
        "position": 45,
        "date": "Dec 20, 2023",
        "sentiment": "positive",
        "probs": {
            "neg": 0.03170708380639553,
            "neu": 0.019583079498261213,
            "pos": 0.9487098157405853
        }
    },
    {
        "title": "Unification Price, Live FUND Market Cap and Chart",
        "snippet": "Crypto News \u00b7 Bitcoin \u00b7 Altcoin \u00b7 Ethereum News \u00b7 Binance Coin News \u00b7 Cardano News \u00b7 Solana News \u00b7 XRP News ... News, Analysis and Markets. Bitcoin News.",
        "highlighted_words": [
            "Ethereum News"
        ],
        "position": 46,
        "date": "Dec 20, 2023",
        "sentiment": "positive",
        "probs": {
            "neg": 0.05233832448720932,
            "neu": 0.031555826775729656,
            "pos": 0.9161058664321899
        }
    },
    {
        "title": "An Afternoon of Science and Teaching",
        "snippet": "News chevron_right; MaP Doctoral School News Channel chevron_right; 2023 ... ETH's Alumni Pavillon. After learning about the school's activities and its ...",
        "highlighted_words": [
            "News",
            "News",
            "ETH's"
        ],
        "position": 47,
        "date": "Dec 21, 2023",
        "sentiment": "positive",
        "probs": {
            "neg": 0.041344975121319294,
            "neu": 0.02414206601679325,
            "pos": 0.9345129728317261
        }
    },
    {
        "title": "Ethereum Price Hovers Around $2190: A Delicate Balance ...",
        "snippet": "Bitcoin News \u00b7 Ethereum News \u00b7 Altcoin News \u00b7 Crypto Prices; Guides. Buy Crypto; Buy Ethereum UK \u00b7 Bitcoin vs. Ripple \u00b7 The Darkside of Bitcoin \u00b7 Pros and Cons ...",
        "highlighted_words": [
            "Ethereum News"
        ],
        "position": 48,
        "date": "Dec 20, 2023",
        "sentiment": "positive",
        "probs": {
            "neg": 0.07645606622099876,
            "neu": 0.10642446577548981,
            "pos": 0.8171194493770599
        }
    },
    {
        "title": "Bitkub \u0e41\u0e1e\u0e25\u0e15\u0e1f\u0e2d\u0e23\u0e4c\u0e21\u0e40\u0e17\u0e23\u0e14\u0e40\u0e2b\u0e23\u0e35\u0e22\u0e0d\u0e14\u0e34\u0e08\u0e34\u0e17\u0e31\u0e25\u0e0a\u0e31\u0e49\u0e19\u0e19\u0e33\u0e43\u0e19\u0e44\u0e17\u0e22 | Bitkub.com",
        "snippet": "\u0e0b\u0e37\u0e49\u0e2d\u0e02\u0e32\u0e22 Bitcoin, Ethereum, USDT, XRP, Dogecoin, Polkadot \u0e41\u0e25\u0e30\u0e40\u0e2b\u0e23\u0e35\u0e22\u0e0d\u0e2d\u0e37\u0e48\u0e19 \u0e46 \u0e14\u0e49\u0e27\u0e22 ... news. \u0e1b\u0e34\u0e14\u0e23\u0e30\u0e1a\u0e1a\u0e1d\u0e32\u0e01\u0e16\u0e2d\u0e19 XTZ (\u0e0a\u0e31\u0e48\u0e27\u0e04\u0e23\u0e32\u0e27) \u0e27\u0e31\u0e19\u0e17\u0e35\u0e48 27/04/68, 19:00 \u0e19. - 20:00 \u0e19 ...",
        "highlighted_words": [
            "Ethereum",
            "news"
        ],
        "position": 49,
        "date": "Dec 20, 2023",
        "sentiment": "positive",
        "probs": {
            "neg": 0.03321763500571251,
            "neu": 0.045191298238933086,
            "pos": 0.9215910732746124
        }
    },
    {
        "title": "Insider Info: Ripple XRP Will Equal Ethereum's $2000 Price ...",
        "snippet": "Insider Info: Ripple XRP Will Equal Ethereum's $2000 Price! (Xrp News Today) In this video Ripple (XRP) is discussed. See the XRP News, what XRP is, ...",
        "highlighted_words": [],
        "position": 50,
        "date": "",
        "sentiment": "positive",
        "probs": {
            "neg": 0.3828943818807602,
            "neu": 0.01060975156724453,
            "pos": 0.6064959019422531
        }
    },
    {
        "title": "Can I Buy a House With Crypto? Yes, Here's How",
        "snippet": "Home / News / Crypto / News / Can I Buy a House With Crypto? Yes ... Most lenders accept Bitcoin (BTC), Ethereum (ETH), and other major cryptocurrencies.",
        "highlighted_words": [
            "News",
            "News",
            "Ethereum",
            "ETH"
        ],
        "position": 51,
        "date": "Dec 23, 2023",
        "sentiment": "positive",
        "probs": {
            "neg": 0.0536524448543787,
            "neu": 0.018328710459172726,
            "pos": 0.9280188679695129
        }
    },
    {
        "title": "Bubble in Stocks, Crypto, Housing Poised for Epic Crash in 2024",
        "snippet": "\"I think 2024 is going to be the biggest single crash year we'll see in our lifetimes,\" Harry Dent told Fox News Digital in an interview published on Tuesday.",
        "highlighted_words": [
            "News"
        ],
        "position": 52,
        "date": "Dec 20, 2023",
        "sentiment": "neutral",
        "probs": {
            "neg": 0.3891735319048166,
            "neu": 0.23440277762711048,
            "pos": 0.3764237314462662
        }
    },
    {
        "title": "Diablo 2 Resurrected Best Builds, Guides, and News",
        "snippet": "Icy Veins provides detailed builds, guides, and news for Diablo 2 Resurrected for all classes: amazon, assassin, barbaria, druid, necromancer, paladin, ...",
        "highlighted_words": [
            "news"
        ],
        "position": 53,
        "date": "Dec 20, 2023",
        "sentiment": "positive",
        "probs": {
            "neg": 0.038266975432634354,
            "neu": 0.02753923274576664,
            "pos": 0.9341937899589539
        }
    },
    {
        "title": "Council of the European Union - Search by document country",
        "snippet": "News and media. Latest news. Press releases \u00b7 Subscribe for updates \u00b7 Discover ... ETH - Ethiopia \u2022 FEDERAL DEMOCRATIC REPUBLIC OF ETHIOPIA \u2022 4 \u00b7 FRO - Faroe ...",
        "highlighted_words": [
            "News",
            "news",
            "ETH"
        ],
        "position": 54,
        "date": "Dec 21, 2023",
        "sentiment": "positive",
        "probs": {
            "neg": 0.024650882929563522,
            "neu": 0.030840137042105198,
            "pos": 0.9445089995861053
        }
    },
    {
        "title": "Buy USDT with USD | P2P Trading",
        "snippet": "News & Announcements \u00b7 Media Kit \u00b7 KuCoin Labs \u00b7 KuCoin Ventures \u00b7 PoR (Proof ... Ethereum (ETH) Price \u00b7 Ripple (XRP) Price \u00b7 KuCoin Token (KCS) Price \u00b7 More ...",
        "highlighted_words": [
            "News",
            "Ethereum",
            "ETH"
        ],
        "position": 55,
        "date": "Dec 22, 2023",
        "sentiment": "positive",
        "probs": {
            "neg": 0.05572343431413174,
            "neu": 0.016631731297820807,
            "pos": 0.9276448786258698
        }
    },
    {
        "title": "VIT\u00c1LIK BUTERIN: qu\u00e9 opina de Argentina, IA y el futuro de ...",
        "snippet": "... Ethereum nos adelanta el roadmap de una de las monedas m\u00e1s populares del ... news https://bit.ly/SuscribiteFilonews Buscamos historias para contar ...",
        "highlighted_words": [],
        "position": 56,
        "date": "",
        "sentiment": "positive",
        "probs": {
            "neg": 0.11861436814069748,
            "neu": 0.017207833006978035,
            "pos": 0.8641777634620667
        }
    },
    {
        "title": "$0.3832\uff5cPOPCAT-USDT USD\u24e2 Margined Perpetual",
        "snippet": "BingX Community. About Us. Work With Us. BingX News. Partners. Log InSign Up. Assets. Total Assets. --USDT. \u2248 $. *Data updates may be delayed. Accounts. Fund ...",
        "highlighted_words": [
            "News"
        ],
        "position": 57,
        "date": "Dec 20, 2023",
        "sentiment": "positive",
        "probs": {
            "neg": 0.15891891345381737,
            "neu": 0.30171999894082546,
            "pos": 0.5393610820174217
        }
    },
    {
        "title": "Will Ethereum overtake Bitcoin in the nearest future?",
        "snippet": "If you mean \u201cwill 1 ETH (aka Ether, aka Ethereum token) ever be worth ... news from reputable sources and take any predictions with a grain of salt ...",
        "highlighted_words": [
            "ETH",
            "Ether",
            "Ethereum",
            "news"
        ],
        "position": 58,
        "date": "",
        "sentiment": "positive",
        "probs": {
            "neg": 0.07486975193023682,
            "neu": 0.014969141688197851,
            "pos": 0.9101610779762268
        }
    },
    {
        "title": "\u0411\u0440\u0430\u0439\u0430\u043d \u0410\u0440\u043c\u0441\u0442\u0440\u043e\u043d\u0433 \u0440\u0430\u0441\u0441\u043a\u0430\u0437\u0430\u043b \u043f\u043e\u043b\u0438\u0442\u0438\u043a\u0430\u043c \u043e \u0440\u043e\u0441\u0442\u0435 ...",
        "snippet": "Bitcoin: 92829.00 $ ; Ethereum: 1750.20 $ ; Litecoin: 83.85 $ ; Ripple: 2.208 $ ; Zcash: 31.38 $.",
        "highlighted_words": [
            "Ethereum"
        ],
        "position": 59,
        "date": "Dec 20, 2023",
        "sentiment": "positive",
        "probs": {
            "neg": 0.10422246158123016,
            "neu": 0.026675961911678314,
            "pos": 0.8691015541553497
        }
    },
    {
        "title": "\u0416\u0438\u0442\u0435\u043b\u044c \u041a\u0430\u0437\u0430\u0445\u0441\u0442\u0430\u043d\u0430 \u043f\u0440\u0435\u0434\u043e\u0441\u0442\u0430\u0432\u043b\u044f\u043b \u043d\u0435\u043b\u0435\u0433\u0430\u043b\u044c\u043d\u044b\u0435 \u0443\u0441\u043b\u0443\u0433\u0438 ...",
        "snippet": "... Ethereum \u0438\u043b\u0438 TRON, \u0430 \u0431\u043b\u0430\u0433\u043e\u0434\u0430\u0440\u044f \u043f\u0440\u043e\u0441\u0442\u044b\u043c. 21.04.2025 0 4 \u043c\u0438\u043d. \u041d\u043e\u0432\u043e\u0441\u0442\u0438 \u043e \u0446\u0438\u0444\u0440\u043e\u0432\u044b\u0445 \u0432\u0430\u043b\u044e\u0442\u0430\u0445, \u0444\u0438\u043d\u0442\u0435\u0445-\u0442\u0440\u0435\u043d\u0434\u0430\u0445 \u0438 \u0444\u0438\u043d\u0430\u043d\u0441\u043e\u0432\u044b\u0445 \u0438\u043d\u043d\u043e\u0432\u0430\u0446\u0438\u044f\u0445. CoinSpot.io - \u043a\u0440\u0443\u043f\u043d\u0435\u0439\u0448\u0438\u0439 \u0432 ...",
        "highlighted_words": [
            "Ethereum"
        ],
        "position": 60,
        "date": "Dec 26, 2023",
        "sentiment": "positive",
        "probs": {
            "neg": 0.09841340780258179,
            "neu": 0.019757304340600967,
            "pos": 0.8818293213844299
        }
    },
    {
        "title": "Impractical Jokers Funniest Moments Mashup | Part 4",
        "snippet": "... news reporting, teaching, scholarship, and research. Fair use is a use ... Ether BROS\u20222.3M views \u00b7 11:25 \u00b7 Go to channel. Impractical Jokers Funniest ...",
        "highlighted_words": [],
        "position": 61,
        "date": "",
        "sentiment": "positive",
        "probs": {
            "neg": 0.04566314071416855,
            "neu": 0.050344616174697876,
            "pos": 0.9039922952651978
        }
    },
    {
        "title": "Cara Kerja Cryptocurrency: Pengertian, Jenis, Dan ...",
        "snippet": "Perbedaan Antara Bitcoin dan Ethereum \u2013 Bitcoin Vs Ethereum \u00b7 Nawi Van -. Ide ... We provide you with the latest breaking news and videos straight from the ...",
        "highlighted_words": [
            "Ethereum",
            "Ethereum",
            "news"
        ],
        "position": 62,
        "date": "Dec 26, 2023",
        "sentiment": "positive",
        "probs": {
            "neg": 0.09273430705070496,
            "neu": 0.012049303855746984,
            "pos": 0.8952164053916931
        }
    },
    {
        "title": "Tips Jitu Meningkatkan Profit Trading Crypto",
        "snippet": "Ethereum (ETH): Koin crypto terbesar kedua di dunia, dengan kapitalisasi ... We provide you with the latest breaking news and videos straight from the Technology ...",
        "highlighted_words": [
            "Ethereum",
            "ETH",
            "news"
        ],
        "position": 63,
        "date": "Dec 26, 2023",
        "sentiment": "positive",
        "probs": {
            "neg": 0.06139858439564705,
            "neu": 0.0189546849578619,
            "pos": 0.919646680355072
        }
    },
    {
        "title": "Baklava (BAVA) Prezzo oggi, grafico e valore in dollari USD",
        "snippet": "... News \u00e8 il principale feed di notizie 24 ore su 7, XNUMX giorni ... Ethereum raggiunge un nuovo record con 449 ETH che entrano negli indirizzi di accumulo.",
        "highlighted_words": [
            "News",
            "Ethereum",
            "ETH"
        ],
        "position": 64,
        "date": "Dec 26, 2023",
        "sentiment": "positive",
        "probs": {
            "neg": 0.08361336588859558,
            "neu": 0.012372049503028393,
            "pos": 0.9040145874023438
        }
    }
]